inteltime
