Metadata-Version: 1.1
Name: inteltime
Version: 1.0.4
Summary: Intel checkpoint and cycle calculator for Niantic Lab's Ingress(tm)
Home-page: https://gitlab.com/pleasantone/intel-times
Author: Paul Traina
Author-email: bulk+pypi@pst.org
License: UNKNOWN
Platform: UNKNOWN
Classifier: Development Status :: 4 - Beta
Classifier: Environment :: Console
Classifier: Environment :: Web Environment
Classifier: License :: OSI Approved :: GNU Affero General Public License v3 or later (AGPLv3+)
Classifier: Natural Language :: English
Classifier: Operating System :: POSIX
Classifier: Programming Language :: Python :: 3.4
Classifier: Programming Language :: Python :: 3.5
Classifier: Topic :: Database :: Front-Ends
Classifier: Topic :: Games/Entertainment
